noobiez/__init__.py
noobiez/connector.py
noobiez/lic.py
noobiez/noobiez.py
noobiez/api/client/__init__.py
noobiez/api/client/discovery.py
noobiez/api/client/resources.py
noobiez/api/client/schemas.py
noobiez-1.8.3.dist-info/METADATA
noobiez-1.8.3.dist-info/WHEEL
noobiez-1.8.3.dist-info/top_level.txt
noobiez-1.8.3.dist-info/RECORD
